odoo/addons/l10n_th_account_tax_multi/README.rst
odoo/addons/l10n_th_account_tax_multi/__init__.py
odoo/addons/l10n_th_account_tax_multi/__manifest__.py
odoo/addons/l10n_th_account_tax_multi/i18n/l10n_th_account_tax_multi.pot
odoo/addons/l10n_th_account_tax_multi/readme/CONTRIBUTORS.rst
odoo/addons/l10n_th_account_tax_multi/readme/DESCRIPTION.rst
odoo/addons/l10n_th_account_tax_multi/readme/USAGE.rst
odoo/addons/l10n_th_account_tax_multi/static/description/icon.png
odoo/addons/l10n_th_account_tax_multi/static/description/index.html
odoo/addons/l10n_th_account_tax_multi/tests/__init__.py
odoo/addons/l10n_th_account_tax_multi/tests/test_account_tax_multi.py
odoo/addons/l10n_th_account_tax_multi/wizard/__init__.py
odoo/addons/l10n_th_account_tax_multi/wizard/account_payment_register.py
odoo/addons/l10n_th_account_tax_multi/wizard/account_payment_register_view.xml
odoo_addon_l10n_th_account_tax_multi-16.0.1.0.0.1.dist-info/METADATA
odoo_addon_l10n_th_account_tax_multi-16.0.1.0.0.1.dist-info/WHEEL
odoo_addon_l10n_th_account_tax_multi-16.0.1.0.0.1.dist-info/top_level.txt
odoo_addon_l10n_th_account_tax_multi-16.0.1.0.0.1.dist-info/RECORD
