Metadata-Version: 2.1
Name: odoo-addon-l10n-th-account-tax-multi
Version: 16.0.1.0.0.1
Summary: Thai Localization - Tax with Payment Multi Deduction
Home-page: https://github.com/OCA/l10n-thailand
Author: Ecosoft, Odoo Community Association (OCA)
Author-email: support@odoo-community.org
License: AGPL-3
Platform: UNKNOWN
Classifier: Programming Language :: Python
Classifier: Framework :: Odoo
Classifier: Framework :: Odoo :: 16.0
Classifier: License :: OSI Approved :: GNU Affero General Public License v3
Classifier: Development Status :: 3 - Alpha
Requires-Python: >=3.10
Requires-Dist: odoo-addon-account-payment-multi-deduction <16.1dev,>=16.0dev
Requires-Dist: odoo-addon-l10n-th-account-tax <16.1dev,>=16.0dev
Requires-Dist: odoo <16.1dev,>=16.0a
